setup.py
integration/__init__.py
integration/auto_plugin_spec.py
integration/default_handler_spec.py
integration/handler_spec.py
integration/host_spec.py
integration/plugin_spec.py
integration/vim_spec.py
integration/_support/__init__.py
integration/_support/base.py
integration/_support/facade.py
integration/_support/handler.py
integration/_support/plugin.py
ribosome/__init__.py
ribosome/cli.py
ribosome/data.py
ribosome/host.py
ribosome/logging.py
ribosome/options.py
ribosome/plugin.py
ribosome/process.py
ribosome/record.py
ribosome/rpc.py
ribosome/settings.py
ribosome.egg-info/PKG-INFO
ribosome.egg-info/SOURCES.txt
ribosome.egg-info/dependency_links.txt
ribosome.egg-info/entry_points.txt
ribosome.egg-info/requires.txt
ribosome.egg-info/top_level.txt
ribosome/machine/__coconut__.py
ribosome/machine/__init__.py
ribosome/machine/base.py
ribosome/machine/handler.py
ribosome/machine/helpers.py
ribosome/machine/machine.py
ribosome/machine/message_base.py
ribosome/machine/messages.py
ribosome/machine/modular.py
ribosome/machine/scratch.py
ribosome/machine/state.py
ribosome/machine/state_a.py
ribosome/machine/state_f.py
ribosome/machine/trans.py
ribosome/machine/transition.py
ribosome/machine/transitions.py
ribosome/nvim/__init__.py
ribosome/nvim/components.py
ribosome/nvim/io.py
ribosome/nvim/scratch.py
ribosome/request/__init__.py
ribosome/request/autocmd.py
ribosome/request/base.py
ribosome/request/command.py
ribosome/request/function.py
ribosome/test/__init__.py
ribosome/test/fixtures.py
ribosome/test/spec.py
ribosome/test/unite.py
ribosome/test/integration/__init__.py
ribosome/test/integration/klk.py
ribosome/test/integration/spec.py
ribosome/test/integration/spec_spec.py
ribosome/unite/__init__.py
ribosome/unite/data.py
ribosome/unite/machine.py
ribosome/unite/plugin.py
ribosome/util/__init__.py
ribosome/util/callback.py