Metadata-Version: 1.0
Name: ribosome
Version: 12.2.1
Summary: neovim plugin framework
Home-page: https://github.com/tek/ribosome
Author: Torsten Schmits
Author-email: torstenschmits@gmail.com
License: MIT
Platform: UNKNOWN
